Verilog_Workspace/FPGA Learning/Shift_Register/shift_register_8bit.v
module shift_register_8bit(
    input  clk,           // 时钟输入
    input  reset,         // 复位输入
    input  shift_left,    // 左移输入
    input  shift_right,   // 右移输入
    input  data_in,       // 数据输入
    output reg [7:0] data // 8位移位寄存器输出
);


always @(posedge clk or negedge reset) begin
    if (!reset) 
        data <= 8'b0; // 复位时，将寄存器清零
     else  if (shift_left) 
            // 左移操作
            data <= {data[6:0], data_in};
     else if (shift_right) 
            // 右移操作
            data <= {data_in, data[7:1]};
        else
            // 无移位操作，仅更新数据
            data <= data_in;
        end

endmodule

Verilog_Workspace/FPGA Learning/Shift_Register/tb_shift_register_8bit;.v
`timescale 1ns / 1ns  // 单位/精度
module tb_shift_register_8bit ();

  reg clk;
  reg reset;
  reg shift_left;
  reg shift_right;
  reg data_in;
  wire [7:0] data;


  // 时钟生成器
  always begin
    #5 clk <= ~clk;
  end

  // 初始化输入信号
  initial begin
    $monitor("%t CLK = %b,Reset = %b,shift_left = %b,shift_right = %b,data_in = %b,Data: %b",
             $time, clk, reset, shift_left, shift_right, data_in, data);

    clk <= 0;
    reset <= 0;
    shift_left <= 0;
    shift_right <= 0;
    data_in <= 0;

    // 等待时钟稳定
    #10 reset <= 1;

    // 输入数据并进行移位操作
    #10 data_in <= 1;
    shift_left <= 1;
    #30 #10 data_in <= 0;
    #20 reset <= 0;
    #20

      // 结束仿真
      $finish;
  end

  initial begin
    $dumpfile("tb_sreg.vcd");
    $dumpvars(0, tb_shift_register_8bit);
  end
  // 实例化被测试的移位寄存器模块
  shift_register_8bit t_shift_reg (
      .clk(clk),
      .reset(reset),
      .shift_left(shift_left),
      .shift_right(shift_right),
      .data_in(data_in),
      .data(data)
  );


endmodule

Verilog_Workspace/FPGA Learning/Shift_Register/tb_shift_reg.vcd
$date
	Sat Nov 04 22:13:38 2023
$end
$version
	Icarus Verilog
$end
$timescale
	1ns
$end
$scope module tb_shift_register_8bit $end
$var wire 8 ! data [7:0] $end
$var reg 1 " clk $end
$var reg 1 # data_in $end
$var reg 1 $ reset $end
$var reg 1 % shift_left $end
$var reg 1 & shift_right $end
$scope module t_shift_reg $end
$var wire 1 " clk $end
$var wire 1 # data_in $end
$var wire 1 $ reset $end
$var wire 1 % shift_left $end
$var wire 1 & shift_right $end
$var reg 8 ' data [7:0] $end
$upscope $end
$upscope $end
$enddefinitions $end
$comment Show the parameter values. $end
$dumpall
$end
#0
$dumpvars
b0 '
0&
0%
0$
0#
0"
b0 !
$end
#5
1"
#10
0"
1$
#15
1"
#20
0"
1%
1#
#25
b1 !
b1 '
1"
#30
0"
#35
b11 !
b11 '
1"
#40
0"
#45
b111 !
b111 '
1"
#50
0"
#55
b1111 !
b1111 '
1"
#60
0"
0#
#65
b11110 !
b11110 '
1"
#70
0"
#75
b111100 !
b111100 '
1"
#80
b0 !
b0 '
0"
0$
